[
  {
    "id": 0,
    "productId": 0,
    "timestamp": "2014-05-20T02:17:00+00:00",
    "user": "User 1",
    "rating": 5,
    "comment": "Aenean vestibulum velit id placerat posuere. Praesent placerat mi ut massa tempor, sed rutrum metus "
  },
  {
    "id": 1,
    "productId": 0,
    "timestamp": "2014-05-20T02:53:00+00:00",
    "user": "User 2",
    "rating": 3,
    "comment": "Aenean vestibulum velit id placerat posuere. Praesent placerat mi ut massa tempor, sed rutrum metus "
  },
  {
    "id": 2,
    "productId": 0,
    "timestamp": "2014-05-20T05:26:00+00:00",
    "user": "User 3",
    "rating": 4,
    "comment": "Aenean vestibulum velit id placerat posuere. Praesent placerat mi ut massa tempor, sed rutrum metus "
  },
  {
    "id": 3,
    "productId": 0,
    "timestamp": "2014-05-20T07:20:00+00:00",
    "user": "User 4",
    "rating": 4,
    "comment": "Aenean vestibulum velit id placerat posuere. Praesent placerat mi ut massa tempor, sed rutrum metus "
  },
  {
    "id": 4,
    "productId": 1,
    "timestamp": "2014-05-20T11:35:00+00:00",
    "user": "User 5",
    "rating": 5,
    "comment": "Aenean vestibulum velit id placerat posuere. Praesent placerat mi ut massa tempor, sed rutrum metus "
  },
  {
    "id": 5,
    "productId": 2,
    "timestamp": "2014-05-20T11:42:00+00:00",
    "user": "User 6",
    "rating": 5,
    "comment": "Aenean vestibulum velit id placerat posuere. Praesent placerat mi ut massa tempor, sed rutrum metus "
  }
]